playground_common_utils/__init__.py
playground_common_utils/convert_data.py
playground_common_utils/files.py
playground_common_utils/http.py
playground_common_utils/logger.py
playground_common_utils-1.4.2.dist-info/METADATA
playground_common_utils-1.4.2.dist-info/WHEEL
playground_common_utils-1.4.2.dist-info/top_level.txt
playground_common_utils-1.4.2.dist-info/RECORD
