Metadata-Version: 2.1
Name: playground-common-utils
Version: 1.4.2
Summary: 汎用ユーティリティ（ファイル操作、ログ出力など）
Home-page: https://github.com/HirokiUmatani/playground-common-utils
Author: Hiroki Umatani
Author-email: h.umatani@playground.style
Classifier: Programming Language :: Python :: 3
Classifier: License :: OSI Approved :: MIT License
Classifier: Operating System :: OS Independent
Requires-Python: >=3.10
Requires-Dist: requests
Requires-Dist: flask
